{"widget_positions":{"wp_inactive_widgets":["block-2","block-3","block-4","block-5","block-6","search-2","recent-posts-2","categories-2","media_image-2","text-2"],"sidebar-1":["search-3","categories-3","recent-posts-3"],"multiblog_footer_1":["text-3"],"multiblog_footer_2":["recent-posts-4"],"multiblog_footer_3":["nav_menu-2"],"multiblog_footer_4":["mc4wp_form_widget-2","tag_cloud-2"],"array_version":3},"widget_options":{"block":{"2":{"content":"<!-- wp:search \/-->"},"3":{"content":"<!-- wp:group --><div class=\"wp-block-group\"><!-- wp:heading --><h2>Recent Posts<\/h2><!-- \/wp:heading --><!-- wp:latest-posts \/--><\/div><!-- \/wp:group -->"},"4":{"content":"<!-- wp:group --><div class=\"wp-block-group\"><!-- wp:heading --><h2>Recent Comments<\/h2><!-- \/wp:heading --><!-- wp:latest-comments {\"displayAvatar\":false,\"displayDate\":false,\"displayExcerpt\":false} \/--><\/div><!-- \/wp:group -->"},"5":{"content":"<!-- wp:group --><div class=\"wp-block-group\"><!-- wp:heading --><h2>Archives<\/h2><!-- \/wp:heading --><!-- wp:archives \/--><\/div><!-- \/wp:group -->"},"6":{"content":"<!-- wp:group --><div class=\"wp-block-group\"><!-- wp:heading --><h2>Categories<\/h2><!-- \/wp:heading --><!-- wp:categories \/--><\/div><!-- \/wp:group -->"},"_multiwidget":1},"search":{"2":{"title":"Search"},"3":{"title":"Search"},"_multiwidget":1},"recent-posts":{"2":{"title":"Recent Posts","number":5,"show_date":false},"3":{"title":"Recent Posts","number":5,"show_date":false},"4":{"title":"Recent Posts","number":5,"show_date":false},"_multiwidget":1},"categories":{"1":[],"2":{"title":"Categories","count":0,"hierarchical":0,"dropdown":0},"3":{"title":"Categories","count":0,"hierarchical":0,"dropdown":0},"_multiwidget":1},"media_image":{"2":{"size":"full","width":560,"height":856,"caption":"","alt":"","link_type":"custom","link_url":"","image_classes":"","link_classes":"","link_rel":"","link_target_blank":false,"image_title":"Advertise with Us","attachment_id":4290,"url":"https:\/\/demo.themesartist.com\/newsmagifypro\/wp-content\/uploads\/2025\/06\/Screenshot-2025-06-22-at-19.32.04.png","title":"Advertise with Us"},"_multiwidget":1},"text":{"1":[],"2":{"title":"Ttitle","text":"dfsdfsdfs\r\n\r\n<a href=\"#\">test<\/a>","filter":true,"visual":true},"3":{"title":"About Us","text":"It is a long established fact that a reader will be distracted by the readable content of a page when looking at its layout.\r\n\r\n4001 Anderson Road, Phoenix AZ\r\ninfo@newsgadgets.com\r\n+(15) 718-999-3939","filter":true,"visual":true},"_multiwidget":1},"nav_menu":{"2":{"title":"Links","nav_menu":40},"_multiwidget":1},"mc4wp_form_widget":{"2":{"title":"Newsletter"},"_multiwidget":1},"tag_cloud":{"2":{"title":"Tags","count":0,"taxonomy":"post_tag"},"_multiwidget":1}}}